qoqo_calculator_pyo3-1.7.1.dist-info/METADATA
qoqo_calculator_pyo3-1.7.1.dist-info/WHEEL
qoqo_calculator_pyo3-1.7.1.dist-info/licenses/LICENSE
qoqo_calculator_pyo3/BSD_LICENSE
qoqo_calculator_pyo3/DEPENDENCIES
qoqo_calculator_pyo3/LICENSE_FOR_BINARY_DISTRIBUTION
qoqo_calculator_pyo3/MIT_LICENSE
qoqo_calculator_pyo3/NOTICE
qoqo_calculator_pyo3/PYTHON_LICENSE
qoqo_calculator_pyo3/__init__.py
qoqo_calculator_pyo3/qoqo_calculator_pyo3.cp39-win_amd64.pyd
qoqo_calculator_pyo3-1.7.1.dist-info/RECORD
