Metadata-Version: 2.4
Name: qoqo_calculator_pyo3
Version: 1.7.1
Requires-Dist: sphinx>=2.1 ; extra == 'docs'
Requires-Dist: nbsphinx ; extra == 'docs'
Requires-Dist: pygments ; extra == 'docs'
Requires-Dist: recommonmark ; extra == 'docs'
Requires-Dist: myst-parser ; extra == 'docs'
Requires-Dist: sphinx-rtd-theme ; extra == 'docs'
Requires-Dist: tomli ; extra == 'docs'
Requires-Dist: numpy ; extra == 'docs'
Provides-Extra: docs
License-File: LICENSE
Author-email: HQS Quantum Simulation GmbH <info@quantumsimulations.de>
Maintainer-email: Matteo Lodi <matteo.lodi@quantumsimulations.de>
License: Apache-2.0 AND Apache-2.0 with LLVM-exception AND MIT AND Unicode-DFS-2016
Requires-Python: >=3.9
